proofy/proofy.py
proofy-0.1.dist-info/METADATA
proofy-0.1.dist-info/WHEEL
proofy-0.1.dist-info/top_level.txt
proofy-0.1.dist-info/RECORD
